harsha_hello_world/__init__.py
harsha_hello_world/cli.py
harsha_hello_world-0.2.dist-info/LICENSE
harsha_hello_world-0.2.dist-info/METADATA
harsha_hello_world-0.2.dist-info/WHEEL
harsha_hello_world-0.2.dist-info/entry_points.txt
harsha_hello_world-0.2.dist-info/top_level.txt
harsha_hello_world-0.2.dist-info/RECORD
